ChatTerminal/__init__.py
ChatTerminal/session.py
tests/__init__.py
tests/terminal_tests.py
ChatTerminal-1.0.1.dist-info/LICENSE
ChatTerminal-1.0.1.dist-info/METADATA
ChatTerminal-1.0.1.dist-info/WHEEL
ChatTerminal-1.0.1.dist-info/top_level.txt
ChatTerminal-1.0.1.dist-info/RECORD
