Metadata-Version: 2.1
Name: ChatTerminal
Version: 1.0.1
Summary: Chat with Servers via SSH
Home-page: https://github.com/chuanwu/ChatTerminal
Author: chuanwu
Author-email: chuanwusun@gmail.com
License: UNKNOWN
Platform: UNKNOWN
Classifier: Programming Language :: Python :: 3
Classifier: License :: OSI Approved :: MIT License
Classifier: Operating System :: OS Independent
